poiolib/WikiExtractor.py
poiolib/__init__.py
poiolib/capitals.py
poiolib/corpus.py
poiolib/langinfo.py
poiolib/ngrams.py
poiolib/wikipedia.py
poiolib/data/README.md
poiolib/data/iso-639-3.tab
poiolib/data/langinfo.json
poiolib/data/update_langinfo.py
poiolib/data/update_langinfo.py~
poiolib-0.1.2.dist-info/LICENSE
poiolib-0.1.2.dist-info/METADATA
poiolib-0.1.2.dist-info/WHEEL
poiolib-0.1.2.dist-info/top_level.txt
poiolib-0.1.2.dist-info/RECORD
