Metadata-Version: 2.1
Name: poiolib
Version: 0.1.2
Summary: A NLP lirary with common functionality of the Poio project.
Home-page: https://github.com/Poio-NLP/poio-lib
Author: Peter Bouda
Author-email: pbouda@outlook.com
License: Apache License, Version 2.0
Platform: UNKNOWN
Classifier: License :: OSI Approved :: Apache Software License
Classifier: Programming Language :: Python
Classifier: Programming Language :: Python :: 3
Classifier: Programming Language :: Python :: 3.6
Requires-Python: >=3.6.0
Requires-Dist: requests
Requires-Dist: beautifulsoup4
Requires-Dist: pressagio
Requires-Dist: regex
Requires-Dist: syntok
